xgo_toolkit/LCD_2inch.py
xgo_toolkit/__init__.py
xgo_toolkit/lcdconfig.py
xgo_toolkit/xgoedu.py
xgo_toolkit/xgolib.py
xgo_toolkit-0.1.6.dist-info/METADATA
xgo_toolkit-0.1.6.dist-info/WHEEL
xgo_toolkit-0.1.6.dist-info/top_level.txt
xgo_toolkit-0.1.6.dist-info/RECORD
