Metadata-Version: 2.1
Name: xgo-toolkit
Version: 0.1.6
Summary: Python Library for XGO-Rider
Home-page: https://github.com/jozolab/xgo-toolkit
Author: JoZoLab
Author-email: github@jozolab.com
License: MIT
Classifier: License :: OSI Approved :: MIT License
Classifier: Programming Language :: Python
Classifier: Programming Language :: Python :: 3
Classifier: Programming Language :: Python :: 3.6
Classifier: Programming Language :: Python :: Implementation :: CPython
Classifier: Programming Language :: Python :: Implementation :: PyPy
Requires-Python: >=3.6.0
